Metadata-Version: 1.0
Name: dsnd-probability-pkg1
Version: 0.1
Summary: Gaussian and Binomial distributions
Home-page: UNKNOWN
Author: PKG Kodikara
Author-email: UNKNOWN
License: UNKNOWN
Platform: UNKNOWN
